{
  "schema": 1,
  "id": 12000,
  "title": "Communication Coach: Two Versions",
  "style": "Writing",
  "placeholders": [
    {
      "name": "message",
      "label": "Message (rough sketch; can be hypothetical)",
      "multiline": true,
      "required": true,
      "default": ""
    },
    {
      "name": "audience",
      "label": "Audience (who will read this; can be hypothetical)",
      "multiline": true,
      "required": true,
      "default": ""
    },
    {
      "name": "tone",
      "label": "Tone (two adjectives, comma-separated; can be aspirational)",
      "multiline": false,
      "required": true,
      "default": ""
    }
  ],
  "template": [
    "## Objective",
    "Transform a rough draft into two audience-appropriate communications (concise and elaborate) the user can paste directly.",
    "",
    "## Context",
    "- Role: expert communication coach.",
    "",
    "## Inputs",
    "- message: {{message}}",
    "- audience: {{audience}}",
    "- tone: {{tone}}",
    "",
    "## Assumptions",
    "Assumption: Inputs may be hypothetical or partially specified; infer sensibly from {{audience}} and {{message}}.",
    "Assumption: {{tone}} has up to two adjectives separated by a comma; if more, use the best two.",
    "Assumption: The user wants copy they can paste as-is with no commentary.",
    "",
    "## Constraints",
    "- Produce exactly two versions and nothing else.",
    "- No salutations or sign-offs unless explicitly asked.",
    "- No meta commentary or preambles.",
    "- Keep token use efficient; avoid redundancy.",
    "",
    "## Instructions",
    "- Keep it simple; remove filler and buzzwords.",
    "- Write conversationally; everyday language and contractions.",
    "- Put the audience first; emphasize benefits, outcomes, next steps.",
    "- Include only what's needed to decide or act.",
    "- Be approachable, confident, optimistic; active voice.",
    "- Sentence case; short sentences/paragraphs; bullets for scanning when helpful.",
    "- Define acronyms on first mention; minimal abbreviations; Oxford comma.",
    "- Numbers: spell 0–9; numerals for 10+, %, and $.",
    "- Be specific about the desired action, owner, and timing.",
    "",
    "## Execution Flow",
    "1) Read inputs.",
    "2) Extract core ask, benefits, next step for the audience.",
    "3) Draft Option 1 (concise).",
    "4) Draft Option 2 (elaborate).",
    "5) Ensure both align to {{tone}} and rules.",
    "6) Output only the two versions in the exact format.",
    "",
    "## Output Format",
    "Option 1 - concise:",
    "[write the concise version here]",
    "",
    "Option 2 - elaborate:",
    "[write the slightly more detailed version here]",
    "",
    "## Quality Checks",
    "- Exactly two versions, nothing else.",
    "- All placeholders inform content; hypotheticals handled sensibly.",
    "- Tone honored; rules followed; minimal verbosity.",
    "",
    "## Eval Stubs",
    "- pass_if(exactly_two_versions == true)",
    "- pass_if(both_versions_name_action_owner_timing == true)",
    "- pass_if(count(sentences_over_20_words) == 0)",
    "",
    "## Self-Check",
    "- Produced only two options with no extra text?",
    "- Both options aligned to {{tone}} and audience needs?",
    "- Concise version minimal and outcome-oriented?",
    "- Elaborate version only slightly longer with necessary context?",
    "- All listed style rules observed?"
  ],
  "metadata": {
    "path": "Writing/communication-coach-two-versions.json",
    "tags": [
      "comms",
      "communication",
      "writing",
      "coach",
      "docs"
    ],
    "version": 1.2,
    "render": "markdown",
    "share_this_file_openly": true,
    "last_edited": "2025-09-24T00:00:00Z"
  },
  "changelog": [
    "2025-09-24: Converted to ordered sections; added Eval Stubs and Self-Check.",
    "2025-09-24: Style set to 'Writing'; path flattened to 'Writing/communication-coach-two-versions.json'.",
    "2025-09-24: Version 1.1 → 1.2; ISO last_edited; globals referenced."
  ]
}
